{"/*":["X-Frame-Options: DENY","X-XSS-Protection: 1; mode=block","X-Content-Type-Options: nosniff","Referrer-Policy: same-origin"],"/styles.ea1b48f9d0396513cb48.css":["Cache-Control: public, max-age=31536000, immutable"],"/commons-9341b3792dc59ac031b5.js":["Cache-Control: public, max-age=31536000, immutable"],"/component---src-pages-404-js-2993b34e030c0d2a1f23.js":["Cache-Control: public, max-age=31536000, immutable"],"/component---src-pages-about-js-eb9e6e7596099518a433.js":["Cache-Control: public, max-age=31536000, immutable"],"/component---src-pages-contact-js-4d1b692b66fbbb667216.js":["Cache-Control: public, max-age=31536000, immutable"],"/component---src-pages-index-js-8a9da15b7b63ee41cad9.js":["Cache-Control: public, max-age=31536000, immutable"],"/webpack-runtime-8ef93337ccd6f4aa0c49.js":["Cache-Control: public, max-age=31536000, immutable"],"/framework-a05f53817e5d25fc6d1e.js":["Cache-Control: public, max-age=31536000, immutable"],"/app-ec5acec09aa87f03b0df.js":["Cache-Control: public, max-age=31536000, immutable"],"/static/*":["Cache-Control: public, max-age=31536000, immutable"],"/sw.js":["Cache-Control: public, max-age=0, must-revalidate"],"/404/":["Link: </webpack-runtime-8ef93337ccd6f4aa0c49.js>; rel=preload; as=script; nopush","Link: </framework-a05f53817e5d25fc6d1e.js>; rel=preload; as=script; nopush","Link: </app-ec5acec09aa87f03b0df.js>; rel=preload; as=script; nopush","Link: </commons-9341b3792dc59ac031b5.js>; rel=preload; as=script; nopush","Link: </component---src-pages-404-js-2993b34e030c0d2a1f23.js>; rel=preload; as=script; nopush","Link: </page-data/app-data.json>; rel=preload; as=fetch; crossorigin; nopush","Link: </page-data/404/page-data.json>; rel=preload; as=fetch; crossorigin; nopush"],"/404.html":["Link: </webpack-runtime-8ef93337ccd6f4aa0c49.js>; rel=preload; as=script; nopush","Link: </framework-a05f53817e5d25fc6d1e.js>; rel=preload; as=script; nopush","Link: </app-ec5acec09aa87f03b0df.js>; rel=preload; as=script; nopush","Link: </commons-9341b3792dc59ac031b5.js>; rel=preload; as=script; nopush","Link: </component---src-pages-404-js-2993b34e030c0d2a1f23.js>; rel=preload; as=script; nopush","Link: </page-data/app-data.json>; rel=preload; as=fetch; crossorigin; nopush","Link: </page-data/404.html/page-data.json>; rel=preload; as=fetch; crossorigin; nopush"],"/about/":["Link: </webpack-runtime-8ef93337ccd6f4aa0c49.js>; rel=preload; as=script; nopush","Link: </framework-a05f53817e5d25fc6d1e.js>; rel=preload; as=script; nopush","Link: </app-ec5acec09aa87f03b0df.js>; rel=preload; as=script; nopush","Link: </commons-9341b3792dc59ac031b5.js>; rel=preload; as=script; nopush","Link: </component---src-pages-about-js-eb9e6e7596099518a433.js>; rel=preload; as=script; nopush","Link: </page-data/app-data.json>; rel=preload; as=fetch; crossorigin; nopush","Link: </page-data/about/page-data.json>; rel=preload; as=fetch; crossorigin; nopush"],"/contact/":["Link: </webpack-runtime-8ef93337ccd6f4aa0c49.js>; rel=preload; as=script; nopush","Link: </framework-a05f53817e5d25fc6d1e.js>; rel=preload; as=script; nopush","Link: </app-ec5acec09aa87f03b0df.js>; rel=preload; as=script; nopush","Link: </commons-9341b3792dc59ac031b5.js>; rel=preload; as=script; nopush","Link: </component---src-pages-contact-js-4d1b692b66fbbb667216.js>; rel=preload; as=script; nopush","Link: </page-data/app-data.json>; rel=preload; as=fetch; crossorigin; nopush","Link: </page-data/contact/page-data.json>; rel=preload; as=fetch; crossorigin; nopush"],"/":["Link: </webpack-runtime-8ef93337ccd6f4aa0c49.js>; rel=preload; as=script; nopush","Link: </framework-a05f53817e5d25fc6d1e.js>; rel=preload; as=script; nopush","Link: </app-ec5acec09aa87f03b0df.js>; rel=preload; as=script; nopush","Link: </commons-9341b3792dc59ac031b5.js>; rel=preload; as=script; nopush","Link: </component---src-pages-index-js-8a9da15b7b63ee41cad9.js>; rel=preload; as=script; nopush","Link: </page-data/app-data.json>; rel=preload; as=fetch; crossorigin; nopush","Link: </page-data/index/page-data.json>; rel=preload; as=fetch; crossorigin; nopush"]}